operators.py
pyloggeritzwazy-2.1.0.dist-info/LICENSE
pyloggeritzwazy-2.1.0.dist-info/METADATA
pyloggeritzwazy-2.1.0.dist-info/WHEEL
pyloggeritzwazy-2.1.0.dist-info/top_level.txt
pyloggeritzwazy-2.1.0.dist-info/RECORD
