Metadata-Version: 2.1
Name: pyloggeritzwazy
Version: 2.1.0
Summary: A simple logging library made in python on 11/21/21
Author-email: ItzWazy <edugabri1217@gmail.com>, Vincenzo Di Maro <vicenzo.dimaro@gmail.com>
Project-URL: Homepage, https://github.com/Legohead69420/pylogger
Project-URL: Issues, https://github.com/Legohead69420/pylogger/issues
Classifier: Programming Language :: Python :: 3
Classifier: License :: OSI Approved :: MIT License
Classifier: Operating System :: OS Independent
Requires-Python: >=3.8
License-File: LICENSE
